librator
