Metadata-Version: 1.1
Name: librator
Version: 0.1.4
Summary: A method of automatically constructing a Librarian library database from a directory of yaml files or the reverse.
Home-page: https://github.com/Nekroze/librator
Author: Taylor "Nekroze" Lawson
Author-email: nekroze@eturnilnetwork.com
License: MIT
Keywords: librator
Platform: UNKNOWN
Classifier: Development Status :: 2 - Pre-Alpha
Classifier: Intended Audience :: Developers
Classifier: License :: OSI Approved :: MIT License
Classifier: Natural Language :: English
Classifier: Programming Language :: Python :: 2
Classifier: Programming Language :: Python :: 2.7
Classifier: Programming Language :: Python :: 3
Classifier: Programming Language :: Python :: 3.3
